txr.py
txr-2.0.1.dist-info/LICENSE
txr-2.0.1.dist-info/METADATA
txr-2.0.1.dist-info/WHEEL
txr-2.0.1.dist-info/entry_points.txt
txr-2.0.1.dist-info/top_level.txt
txr-2.0.1.dist-info/RECORD
