Metadata-Version: 2.1
Name: txr
Version: 2.0.1
Summary: TXR: The teXt aRchiver - archives text as text. and much more.
Home-page: https://github.com/idanmiara/txr
Author: Idan Miara
Author-email: idan@miara.com
License: GPL3
Classifier: Development Status :: 5 - Production/Stable
Classifier: Intended Audience :: Developers
Classifier: Intended Audience :: Science/Research
Classifier: License :: OSI Approved :: MIT License
Classifier: Operating System :: OS Independent
Classifier: Programming Language :: Python :: 3
Requires-Python: >=3.6.0
License-File: LICENSE
Provides-Extra: crypto
Requires-Dist: cryptography ; extra == 'crypto'
